README.md
setup.cfg
setup.py
taylor_instrument/CustomCompositeLogger.py
taylor_instrument/__init__.py
taylor_instrument/instrument.py
taylor_instrument/metrics.py
taylor_instrument.egg-info/PKG-INFO
taylor_instrument.egg-info/SOURCES.txt
taylor_instrument.egg-info/dependency_links.txt
taylor_instrument.egg-info/requires.txt
taylor_instrument.egg-info/top_level.txt
taylor_instrument.egg-info/zip-safe