Metadata-Version: 2.1
Name: taylor-instrument
Version: 0.0.8
Summary: Instrument service for logs and metrics
Home-page: UNKNOWN
Author: 
Author-email: 
License: UNKNOWN
Platform: any
Classifier: Development Status :: 4 - Beta
Classifier: Intended Audience :: Developers
Classifier: License :: OSI Approved :: MIT License
Classifier: Operating System :: OS Independent
Classifier: Programming Language :: Python
Classifier: Programming Language :: Python :: 3.7
Classifier: Programming Language :: Python :: 3.8
Classifier: Topic :: Software Development :: Libraries :: Python Modules
